setup.py
gradale/__init__.py
gradale/shortcuts.py
gradale.egg-info/PKG-INFO
gradale.egg-info/SOURCES.txt
gradale.egg-info/dependency_links.txt
gradale.egg-info/not-zip-safe
gradale.egg-info/pbr.json
gradale.egg-info/top_level.txt
gradale/components/__init__.py
gradale/components/nodes.py
gradale/tests/__init__.py
gradale/tests/base.py
gradale/tests/list/__init__.py
gradale/tests/list/tests.py
gradale/tests/nodes/__init__.py
gradale/tests/nodes/tests.py
gradale/utils/__init__.py
gradale/utils/console.py
gradale/utils/decorators.py
gradale/utils/iter.py
gradale/utils/nodes.py