Metadata-Version: 1.1
Name: gradale
Version: 3
Summary: Package description
